log2db/Log2DB.py
log2db/__init__.py
log2db/CompareLog/Compare.py
log2db/CompareLog/__init__.py
log2db/GetResult/Private_Save_Result.py
log2db/GetResult/Save_Result.py
log2db/GetResult/__init__.py
log2db/Server/MongoServer.py
log2db/Server/__init__.py
log2db-0.0.3.dist-info/LICENSE
log2db-0.0.3.dist-info/METADATA
log2db-0.0.3.dist-info/WHEEL
log2db-0.0.3.dist-info/top_level.txt
log2db-0.0.3.dist-info/RECORD
